README.md
setup.cfg
setup.py
bin/fire
fireml/__init__.py
fireml/activecache.py
fireml/balance.py
fireml/builder.py
fireml/caffe_pb2.py
fireml/common-vrep.py
fireml/common.py
fireml/concat_layer.py
fireml/const.py
fireml/conv.py
fireml/conv_layer.py
fireml/cost.py
fireml/data_reader.py
fireml/debug.py
fireml/fire_pb2.py
fireml/fireml_tests.py
fireml/gen_testset.py
fireml/image_data_reader.py
fireml/learning.py
fireml/logistic_sgd.py
fireml/lstm.py
fireml/mlp.py
fireml/noise.py
fireml/preprocessor.py
fireml/relu.py
fireml/softmax.py
fireml/train.py
fireml/utils.py
fireml/weight_filler.py
fireml/weights_to_pickle.py
fireml.egg-info/PKG-INFO
fireml.egg-info/SOURCES.txt
fireml.egg-info/dependency_links.txt
fireml.egg-info/requires.txt
fireml.egg-info/top_level.txt
scripts/balance.py
scripts/gen_testset.py