Metadata-Version: 2.1
Name: fireml
Version: 0.1.1
Summary: fireml machine learning framework
Home-page: https://bitbucket.org/noSkill/fireml
Author: Anatoly Belikov
Author-email: awbelikov@gmail.com
License: UNKNOWN
Platform: UNKNOWN
